ohlcv_to_orderbook/__init__.py
ohlcv_to_orderbook/_version.py
ohlcv_to_orderbook/cli.py
ohlcv_to_orderbook/config.py
ohlcv_to_orderbook/data_types.py
ohlcv_to_orderbook/exceptions.py
ohlcv_to_orderbook/io_handlers.py
ohlcv_to_orderbook/ohlcv_to_orderbook.py
ohlcv_to_orderbook/orderbook_to_ohlcv.py
ohlcv_to_orderbook/synthetic_data.py
ohlcv_to_orderbook-0.1.8.dist-info/licenses/LICENSE
ohlcv_to_orderbook-0.1.8.dist-info/METADATA
ohlcv_to_orderbook-0.1.8.dist-info/WHEEL
ohlcv_to_orderbook-0.1.8.dist-info/entry_points.txt
ohlcv_to_orderbook-0.1.8.dist-info/top_level.txt
ohlcv_to_orderbook-0.1.8.dist-info/RECORD
