Metadata-Version: 2.4
Name: ohlcv-to-orderbook
Version: 0.1.8
Summary: Convert OHLCV data to order book data and vice versa
Author-email: Luca Forni <obseries@outlook.com>
License: MIT License
Project-URL: Homepage, https://github.com/obseries/ohlcv-to-orderbook
Project-URL: Repository, https://github.com/obseries/ohlcv-to-orderbook
Project-URL: Issues, https://github.com/obseries/ohlcv-to-orderbook/issues
Classifier: Development Status :: 4 - Beta
Classifier: Intended Audience :: Developers
Classifier: License :: OSI Approved :: MIT License
Classifier: Programming Language :: Python :: 3
Classifier: Programming Language :: Python :: 3.8
Classifier: Programming Language :: Python :: 3.9
Classifier: Programming Language :: Python :: 3.10
Classifier: Programming Language :: Python :: 3.11
Classifier: Programming Language :: Python :: 3.12
Classifier: Programming Language :: Python :: 3.13
Requires-Python: >=3.8
License-File: LICENSE
Requires-Dist: pandas>=2.0.0
Requires-Dist: numpy>=1.20.0
Requires-Dist: pyarrow>=5.0.0
Provides-Extra: dev
Requires-Dist: pytest>=6.0; extra == "dev"
Requires-Dist: pytest-cov; extra == "dev"
Requires-Dist: black; extra == "dev"
Requires-Dist: isort; extra == "dev"
Requires-Dist: mypy; extra == "dev"
Requires-Dist: pandas-stubs; extra == "dev"
Dynamic: license-file
